helios_websocket_api/__init__.py
helios_websocket_api/client.py
helios_websocket_api/exceptions.py
helios_websocket_api/helios.py
helios_websocket_api/messages.py
helios_websocket_api/py.typed
helios_websocket_api/data/2.0.16.json
helios_websocket_api/data/2.0.22.json
helios_websocket_api/data/__init__.py
helios_websocket_api/data/constants.py
helios_websocket_api/data/model.py
helios_websocket_api-1.0.0.dist-info/licenses/LICENSE.txt
helios_websocket_api-1.0.0.dist-info/METADATA
helios_websocket_api-1.0.0.dist-info/WHEEL
helios_websocket_api-1.0.0.dist-info/top_level.txt
helios_websocket_api-1.0.0.dist-info/zip-safe
helios_websocket_api-1.0.0.dist-info/RECORD
