Metadata-Version: 2.4
Name: helios_websocket_api
Version: 1.0.0
Summary: Helios WebSocket API
Home-page: https://github.com/helios-ventilatoren-com/helios_websocket_api
Author: Jan Späth
Author-email: j.spaeth@heliosventilatoren.de
License: LGPL 3
Project-URL: Bug Tracker, https://github.com/helios-ventilatoren-com/helios_websocket_api/issues
Keywords: helios api
Classifier: Development Status :: 5 - Production/Stable
Classifier: Intended Audience :: Developers
Classifier: License :: OSI Approved :: GNU Lesser General Public License v3 (LGPLv3)
Classifier: Operating System :: OS Independent
Classifier: Programming Language :: Python
Classifier: Programming Language :: Python :: 3 :: Only
Classifier: Programming Language :: Python :: 3.9
Classifier: Programming Language :: Python :: 3.10
Classifier: Programming Language :: Python :: 3.11
Classifier: Programming Language :: Python :: 3.12
Classifier: Programming Language :: Python :: 3.13
Classifier: Programming Language :: Python :: 3.14
Requires-Python: <4,>=3.9.0
License-File: LICENSE.txt
Requires-Dist: websockets>=9.1
Requires-Dist: construct<3.0.0,>=2.9.0
Requires-Dist: aiohttp<4.0.0,>=3.7.0
Dynamic: license-file
